helloworld.py
helloworld_tal1948_3-0.0.1.dist-info/LICENSE.txt
helloworld_tal1948_3-0.0.1.dist-info/METADATA
helloworld_tal1948_3-0.0.1.dist-info/WHEEL
helloworld_tal1948_3-0.0.1.dist-info/top_level.txt
helloworld_tal1948_3-0.0.1.dist-info/RECORD
